{
  "result": "success",
  "photos": [
    {
      "gif": "http://sbviewer.com/photos/1450763327.gif",
      "jpg": "http://sbviewer.com/photos/1450763327.jpg"
    },
    {
      "gif": "http://sbviewer.com/photos/1450732828.gif",
      "jpg": "https://placebear.com/200/200"
    },
    {
      "gif": "http://sbviewer.com/photos/1450732835.gif",
      "jpg": "https://placebear.com/201/201"
    },
    {
      "gif": "http://sbviewer.com/photos/1450732838.gif",
      "jpg": "https://placebear.com/202/202"
    }
  ]
}
